<annotation verified="no">
  <folder>T22L600_renamed_detected</folder>
  <filename>T22L600_W1_GC1_R2_P125_g83_2</filename>
  <path>C:/Users/Administrator/seadrive_root/Mahmoud/Shared with me/Constantin/Marc_ProScope/T22L600_renamed_detected/T22L600_W1_GC1_R2_P125_g83_2.jpg</path>
  <source>
    <database>Unknown</database>
  </source>
  <size>
    <width>2592</width>
    <height>1944</height>
    <depth>3</depth>
  </size>
  <segmented>0</segmented>
  <object>
    <type>robndbox</type>
    <name>blurry.complete</name>
    <pose>Unspecified</pose>
    <truncated>0</truncated>
    <difficult>0</difficult>
    <robndbox>
      <cx>134.0244</cx>
      <cy>562.8659</cy>
      <w>200.0</w>
      <h>107.0</h>
      <angle>0.067111</angle>
    </robndbox>
  </object>
  <object>
    <type>robndbox</type>
    <name>blurry.complete</name>
    <pose>Unspecified</pose>
    <truncated>0</truncated>
    <difficult>0</difficult>
    <robndbox>
      <cx>835.5244</cx>
      <cy>589.3659</cy>
      <w>247.0</w>
      <h>100.0</h>
      <angle>0.053104</angle>
    </robndbox>
  </object>
  <object>
    <type>robndbox</type>
    <name>blurry.complete</name>
    <pose>Unspecified</pose>
    <truncated>0</truncated>
    <difficult>0</difficult>
    <robndbox>
      <cx>1431.0244</cx>
      <cy>605.8659</cy>
      <w>210.0</w>
      <h>97.0</h>
      <angle>0.117991</angle>
    </robndbox>
  </object>
  <object>
    <type>robndbox</type>
    <name>complete</name>
    <pose>Unspecified</pose>
    <truncated>0</truncated>
    <difficult>0</difficult>
    <robndbox>
      <cx>1937.5244</cx>
      <cy>613.3659</cy>
      <w>227.0</w>
      <h>90.0</h>
      <angle>0.064</angle>
    </robndbox>
  </object>
  <object>
    <type>robndbox</type>
    <name>complete</name>
    <pose>Unspecified</pose>
    <truncated>0</truncated>
    <difficult>0</difficult>
    <robndbox>
      <cx>2459.4914</cx>
      <cy>624.6413</cy>
      <w>216.9339</w>
      <h>98.5508</h>
      <angle>0.067011</angle>
    </robndbox>
  </object>
  <object>
    <type>robndbox</type>
    <name>complete</name>
    <pose>Unspecified</pose>
    <truncated>0</truncated>
    <difficult>0</difficult>
    <robndbox>
      <cx>261.7754</cx>
      <cy>1174.6187</cy>
      <w>232.375</w>
      <h>99.8533</h>
      <angle>0.056398</angle>
    </robndbox>
  </object>
  <object>
    <type>robndbox</type>
    <name>complete</name>
    <pose>Unspecified</pose>
    <truncated>0</truncated>
    <difficult>0</difficult>
    <robndbox>
      <cx>815.9914</cx>
      <cy>1199.6413</cy>
      <w>226.0661</w>
      <h>98.5508</h>
      <angle>0.0</angle>
    </robndbox>
  </object>
  <object>
    <type>robndbox</type>
    <name>complete</name>
    <pose>Unspecified</pose>
    <truncated>0</truncated>
    <difficult>0</difficult>
    <robndbox>
      <cx>1308.5244</cx>
      <cy>1206.3659</cy>
      <w>227.0</w>
      <h>110.0</h>
      <angle>0.0</angle>
    </robndbox>
  </object>
  <object>
    <type>robndbox</type>
    <name>complete</name>
    <pose>Unspecified</pose>
    <truncated>0</truncated>
    <difficult>0</difficult>
    <robndbox>
      <cx>1868.9583</cx>
      <cy>1218.6413</cy>
      <w>236.0</w>
      <h>106.5508</h>
      <angle>0.0</angle>
    </robndbox>
  </object>
  <object>
    <type>robndbox</type>
    <name>complete</name>
    <pose>Unspecified</pose>
    <truncated>0</truncated>
    <difficult>0</difficult>
    <robndbox>
      <cx>2431.5244</cx>
      <cy>1221.8659</cy>
      <w>225.0</w>
      <h>97.0</h>
      <angle>0.0</angle>
    </robndbox>
  </object>
  <object>
    <type>robndbox</type>
    <name>blurry.incomplete</name>
    <pose>Unspecified</pose>
    <truncated>0</truncated>
    <difficult>0</difficult>
    <robndbox>
      <cx>54.5122</cx>
      <cy>1858.2502</cy>
      <w>109.0244</w>
      <h>91.7687</h>
      <angle>0.0</angle>
    </robndbox>
  </object>
  <object>
    <type>robndbox</type>
    <name>blurry.complete</name>
    <pose>Unspecified</pose>
    <truncated>0</truncated>
    <difficult>0</difficult>
    <robndbox>
      <cx>571.5244</cx>
      <cy>1873.3659</cy>
      <w>213.0</w>
      <h>98.0</h>
      <angle>0.0</angle>
    </robndbox>
  </object>
  <object>
    <type>robndbox</type>
    <name>blurry.complete</name>
    <pose>Unspecified</pose>
    <truncated>0</truncated>
    <difficult>0</difficult>
    <robndbox>
      <cx>1086.0244</cx>
      <cy>1887.8659</cy>
      <w>232.0</w>
      <h>103.0</h>
      <angle>0.0</angle>
    </robndbox>
  </object>
  <object>
    <type>robndbox</type>
    <name>blurry.incomplete</name>
    <pose>Unspecified</pose>
    <truncated>0</truncated>
    <difficult>0</difficult>
    <robndbox>
      <cx>1905.49</cx>
      <cy>1907.1829</cy>
      <w>210.9311</w>
      <h>73.6341</h>
      <angle>0.0</angle>
    </robndbox>
  </object>
  <object>
    <type>robndbox</type>
    <name>blurry.incomplete</name>
    <pose>Unspecified</pose>
    <truncated>0</truncated>
    <difficult>0</difficult>
    <robndbox>
      <cx>2496.415</cx>
      <cy>1912.1829</cy>
      <w>188.7813</w>
      <h>63.6341</h>
      <angle>0.0</angle>
    </robndbox>
  </object>
  <object>
    <type>robndbox</type>
    <name>hair</name>
    <pose>Unspecified</pose>
    <truncated>0</truncated>
    <difficult>0</difficult>
    <robndbox>
      <cx>1235.5244</cx>
      <cy>533.8659</cy>
      <w>103.0</w>
      <h>75.0</h>
      <angle>0.0</angle>
    </robndbox>
  </object>
</annotation>
