<annotation verified="no">
  <folder>T22L600_renamed_detected</folder>
  <filename>T22L600_W1_GC1_R2_P129_g48_5</filename>
  <path>C:/Users/zamzam/seadrive_root/Mahmoud/Shared with me/Constantin/Marc_ProScope/T22L600_renamed_detected/T22L600_W1_GC1_R2_P129_g48_5.jpg</path>
  <source>
    <database>Unknown</database>
  </source>
  <size>
    <width>2592</width>
    <height>1944</height>
    <depth>3</depth>
  </size>
  <segmented>0</segmented>
  <object>
    <type>robndbox</type>
    <name>incomplete</name>
    <pose>Unspecified</pose>
    <truncated>0</truncated>
    <difficult>0</difficult>
    <robndbox>
      <cx>30.5122</cx>
      <cy>501.4895</cy>
      <w>61.0244</w>
      <h>90.2473</h>
      <angle>0.0</angle>
    </robndbox>
  </object>
  <object>
    <type>robndbox</type>
    <name>complete</name>
    <pose>Unspecified</pose>
    <truncated>0</truncated>
    <difficult>0</difficult>
    <robndbox>
      <cx>422.5882</cx>
      <cy>488.9182</cy>
      <w>232.0</w>
      <h>95.1047</h>
      <angle>0.0</angle>
    </robndbox>
  </object>
  <object>
    <type>robndbox</type>
    <name>complete</name>
    <pose>Unspecified</pose>
    <truncated>0</truncated>
    <difficult>0</difficult>
    <robndbox>
      <cx>881.5244</cx>
      <cy>488.8659</cy>
      <w>197.0</w>
      <h>105.0</h>
      <angle>0.0</angle>
    </robndbox>
  </object>
  <object>
    <type>robndbox</type>
    <name>complete</name>
    <pose>Unspecified</pose>
    <truncated>0</truncated>
    <difficult>0</difficult>
    <robndbox>
      <cx>1236.5244</cx>
      <cy>492.8659</cy>
      <w>195.0</w>
      <h>97.0</h>
      <angle>0.0</angle>
    </robndbox>
  </object>
  <object>
    <type>robndbox</type>
    <name>complete</name>
    <pose>Unspecified</pose>
    <truncated>0</truncated>
    <difficult>0</difficult>
    <robndbox>
      <cx>1658.5244</cx>
      <cy>492.8659</cy>
      <w>205.0</w>
      <h>93.0</h>
      <angle>0.0</angle>
    </robndbox>
  </object>
  <object>
    <type>robndbox</type>
    <name>complete</name>
    <pose>Unspecified</pose>
    <truncated>0</truncated>
    <difficult>0</difficult>
    <robndbox>
      <cx>1996.0244</cx>
      <cy>490.3659</cy>
      <w>182.0</w>
      <h>102.0</h>
      <angle>0.0</angle>
    </robndbox>
  </object>
  <object>
    <type>robndbox</type>
    <name>complete</name>
    <pose>Unspecified</pose>
    <truncated>0</truncated>
    <difficult>0</difficult>
    <robndbox>
      <cx>2341.5244</cx>
      <cy>502.3659</cy>
      <w>195.0</w>
      <h>102.0</h>
      <angle>0.0</angle>
    </robndbox>
  </object>
  <object>
    <type>robndbox</type>
    <name>complete</name>
    <pose>Unspecified</pose>
    <truncated>0</truncated>
    <difficult>0</difficult>
    <robndbox>
      <cx>128.0244</cx>
      <cy>1003.3659</cy>
      <w>178.0</w>
      <h>90.0</h>
      <angle>0.0</angle>
    </robndbox>
  </object>
  <object>
    <type>robndbox</type>
    <name>complete</name>
    <pose>Unspecified</pose>
    <truncated>0</truncated>
    <difficult>0</difficult>
    <robndbox>
      <cx>409.5244</cx>
      <cy>1008.3659</cy>
      <w>171.0</w>
      <h>110.0</h>
      <angle>0.0</angle>
    </robndbox>
  </object>
  <object>
    <type>robndbox</type>
    <name>complete</name>
    <pose>Unspecified</pose>
    <truncated>0</truncated>
    <difficult>0</difficult>
    <robndbox>
      <cx>694.5244</cx>
      <cy>1008.8659</cy>
      <w>185.0</w>
      <h>85.0</h>
      <angle>0.0</angle>
    </robndbox>
  </object>
  <object>
    <type>robndbox</type>
    <name>complete</name>
    <pose>Unspecified</pose>
    <truncated>0</truncated>
    <difficult>0</difficult>
    <robndbox>
      <cx>1005.3063</cx>
      <cy>1016.4182</cy>
      <w>196.5638</w>
      <h>100.1047</h>
      <angle>0.0</angle>
    </robndbox>
  </object>
  <object>
    <type>robndbox</type>
    <name>complete</name>
    <pose>Unspecified</pose>
    <truncated>0</truncated>
    <difficult>0</difficult>
    <robndbox>
      <cx>1308.0244</cx>
      <cy>1016.8659</cy>
      <w>222.0</w>
      <h>93.0</h>
      <angle>0.0</angle>
    </robndbox>
  </object>
  <object>
    <type>robndbox</type>
    <name>complete</name>
    <pose>Unspecified</pose>
    <truncated>0</truncated>
    <difficult>0</difficult>
    <robndbox>
      <cx>1713.0244</cx>
      <cy>1013.3659</cy>
      <w>202.0</w>
      <h>90.0</h>
      <angle>0.0</angle>
    </robndbox>
  </object>
  <object>
    <type>robndbox</type>
    <name>complete</name>
    <pose>Unspecified</pose>
    <truncated>0</truncated>
    <difficult>0</difficult>
    <robndbox>
      <cx>2074.3063</cx>
      <cy>1007.9182</cy>
      <w>217.4362</w>
      <h>93.1047</h>
      <angle>0.0</angle>
    </robndbox>
  </object>
  <object>
    <type>robndbox</type>
    <name>complete</name>
    <pose>Unspecified</pose>
    <truncated>0</truncated>
    <difficult>0</difficult>
    <robndbox>
      <cx>2495.3063</cx>
      <cy>1011.9182</cy>
      <w>189.4362</w>
      <h>97.1047</h>
      <angle>0.0</angle>
    </robndbox>
  </object>
  <object>
    <type>robndbox</type>
    <name>blurry.complete</name>
    <pose>Unspecified</pose>
    <truncated>0</truncated>
    <difficult>0</difficult>
    <robndbox>
      <cx>387.3063</cx>
      <cy>1893.2353</cy>
      <w>208.5638</w>
      <h>101.5294</h>
      <angle>0.0</angle>
    </robndbox>
  </object>
  <object>
    <type>robndbox</type>
    <name>blurry.complete</name>
    <pose>Unspecified</pose>
    <truncated>0</truncated>
    <difficult>0</difficult>
    <robndbox>
      <cx>756.334</cx>
      <cy>1890.1829</cy>
      <w>206.6191</w>
      <h>107.6341</h>
      <angle>0.0</angle>
    </robndbox>
  </object>
  <object>
    <type>robndbox</type>
    <name>blurry.incomplete</name>
    <pose>Unspecified</pose>
    <truncated>0</truncated>
    <difficult>0</difficult>
    <robndbox>
      <cx>1155.3063</cx>
      <cy>1892.9706</cy>
      <w>202.5638</w>
      <h>99.0</h>
      <angle>0.0</angle>
    </robndbox>
  </object>
  <object>
    <type>robndbox</type>
    <name>blurry.complete</name>
    <pose>Unspecified</pose>
    <truncated>0</truncated>
    <difficult>0</difficult>
    <robndbox>
      <cx>1815.9018</cx>
      <cy>1891.6829</cy>
      <w>187.7547</w>
      <h>104.6341</h>
      <angle>0.0</angle>
    </robndbox>
  </object>
  <object>
    <type>robndbox</type>
    <name>blurry.incomplete</name>
    <pose>Unspecified</pose>
    <truncated>0</truncated>
    <difficult>0</difficult>
    <robndbox>
      <cx>2442.3069</cx>
      <cy>1898.7353</cy>
      <w>207.4374</w>
      <h>88.5294</h>
      <angle>0.0</angle>
    </robndbox>
  </object>
  <object>
    <type>robndbox</type>
    <name>blurry.complete</name>
    <pose>Unspecified</pose>
    <truncated>0</truncated>
    <difficult>0</difficult>
    <robndbox>
      <cx>2152.3063</cx>
      <cy>1849.9182</cy>
      <w>206.5638</w>
      <h>97.1047</h>
      <angle>0.0</angle>
    </robndbox>
  </object>
  <object>
    <type>robndbox</type>
    <name>blurry.incomplete</name>
    <pose>Unspecified</pose>
    <truncated>0</truncated>
    <difficult>0</difficult>
    <robndbox>
      <cx>73.7941</cx>
      <cy>1839.4182</cy>
      <w>147.5882</w>
      <h>118.1047</h>
      <angle>0.0</angle>
    </robndbox>
  </object>
  <object>
    <type>robndbox</type>
    <name>hair</name>
    <pose>Unspecified</pose>
    <truncated>0</truncated>
    <difficult>0</difficult>
    <robndbox>
      <cx>543.6285</cx>
      <cy>1453.4214</cy>
      <w>71.5943</w>
      <h>94.1053</h>
      <angle>0.233106</angle>
    </robndbox>
  </object>
  <object>
    <type>robndbox</type>
    <name>hair</name>
    <pose>Unspecified</pose>
    <truncated>0</truncated>
    <difficult>0</difficult>
    <robndbox>
      <cx>2104.5244</cx>
      <cy>1478.3659</cy>
      <w>107.0</w>
      <h>102.0</h>
      <angle>0.0</angle>
    </robndbox>
  </object>
</annotation>
